voipms/__init__.py
voipms/api/__init__.py
voipms/api/accounts/__init__.py
voipms/api/accounts/registration_status.py
voipms/api/accounts/subaccount.py
voipms/api/call_detail_records/__init__.py
voipms/api/call_detail_records/billing.py
voipms/api/call_detail_records/rates.py
voipms/api/call_detail_records/records.py
voipms/api/call_detail_records/termination_rates.py
voipms/api/dids/__init__.py
voipms/api/dids/search.py
voipms/api/dids/sms.py
voipms/api/general/__init__.py
voipms/api/general/balance.py
voipms/api/general/countries.py
voipms/api/general/ip.py
voipms/api/general/languages.py
voipms/api/general/transaction_history.py
voipms/api/voicemail/__init__.py
voipms/api/voicemail/messages.py
voipms/base/__init__.py
voipms/base/exceptions.py
voipms/base/values.py
voipms_python-0.0.2.dist-info/LICENSE.txt
voipms_python-0.0.2.dist-info/METADATA
voipms_python-0.0.2.dist-info/WHEEL
voipms_python-0.0.2.dist-info/top_level.txt
voipms_python-0.0.2.dist-info/RECORD
