Metadata-Version: 2.1
Name: voipms-python
Version: 0.0.2
Summary: Python wrapper for the voip.ms REST API
Home-page: https://github.com/dtesfai/voipms-python
Author: Daniel Tesfai
Author-email: danielmtesfai@gmail.com
License: MIT
Project-URL: Bug Tracker, https://github.com/dtesfai/voipms-python/issues
Project-URL: Source Code, https://github.com/dtesfai/voipms-python
Keywords: voipms api
Platform: UNKNOWN
Classifier: Development Status :: 2 - Pre-Alpha
Classifier: Intended Audience :: Developers
Classifier: License :: OSI Approved :: MIT License
Classifier: Operating System :: OS Independent
Classifier: Programming Language :: Python :: 3
Classifier: Programming Language :: Python :: 3.4
Classifier: Programming Language :: Python :: 3.5
Classifier: Programming Language :: Python :: 3.6
Classifier: Programming Language :: Python :: 3.7
Classifier: Programming Language :: Python :: Implementation :: PyPy
Classifier: Topic :: Software Development :: Libraries :: Python Modules
Requires-Python: >=3.4
